brq/__init__.py
brq/browser.py
brq/cli.py
brq/configs.py
brq/consumer.py
brq/daemon.py
brq/decorator.py
brq/envs.py
brq/log.py
brq/models.py
brq/operator.py
brq/producer.py
brq/rds.py
brq/tools.py
brq-0.5.0.dist-info/METADATA
brq-0.5.0.dist-info/WHEEL
brq-0.5.0.dist-info/entry_points.txt
brq-0.5.0.dist-info/licenses/LICENSE
brq-0.5.0.dist-info/RECORD
