Metadata-Version: 2.3
Name: brq
Version: 0.5.0
Summary: brq
Project-URL: Source, https://github.com/b-scheduler/brq
Author-email: wh1isper <jizhongsheng957@gmail.com>
License: BSD 3-Clause License
License-File: LICENSE
Keywords: brq
Classifier: Programming Language :: Python :: 3
Classifier: Programming Language :: Python :: 3.10
Classifier: Programming Language :: Python :: 3.11
Classifier: Programming Language :: Python :: 3.12
Requires-Python: >=3.10
Requires-Dist: anyio
Requires-Dist: click
Requires-Dist: loguru
Requires-Dist: pydantic-settings
Requires-Dist: pydantic<3,>=2
Requires-Dist: redis<6,>=5.0
Provides-Extra: browser
Requires-Dist: fastapi; extra == 'browser'
Requires-Dist: uvicorn[standard]; extra == 'browser'
Provides-Extra: docs
Requires-Dist: autodoc-pydantic; extra == 'docs'
Requires-Dist: pydata-sphinx-theme; extra == 'docs'
Requires-Dist: sphinx; extra == 'docs'
Requires-Dist: sphinx-click; extra == 'docs'
Provides-Extra: test
Requires-Dist: docker; extra == 'test'
Requires-Dist: fastapi; extra == 'test'
Requires-Dist: pytest; extra == 'test'
Requires-Dist: pytest-asyncio; extra == 'test'
Requires-Dist: pytest-cov; extra == 'test'
Requires-Dist: uvicorn[standard]; extra == 'test'
